astrodatapy/__init__.py
astrodatapy/_astropy_init.py
astrodatapy/clustering.py
astrodatapy/conftest.py
astrodatapy/correlation.py
astrodatapy/magnitudes.py
astrodatapy/misc_tools.py
astrodatapy/number_density.py
astrodatapy/version.py
astrodatapy/data/README.rst
astrodatapy/data/bibliography.bib
astrodatapy/data/BHM/info.txt
astrodatapy/data/BHM/Caramete2010/z0pt0.dat
astrodatapy/data/BHMF/info.txt
astrodatapy/data/BHMF/Davis2014/z0pt0.dat
astrodatapy/data/BHMF/Graham2007/z0pt0.dat
astrodatapy/data/BHMF/Mutlu-Pakdil2016/z0pt0.dat
astrodatapy/data/BHMF/Qin2017_Tiamat/z2pt00.dat
astrodatapy/data/BHMF/Qin2017_Tiamat/z4pt02.dat
astrodatapy/data/BHMF/Qin2017_Tiamat/z5pt00.dat
astrodatapy/data/BHMF/Qin2017_Tiamat/z7pt96.dat
astrodatapy/data/BHMF/Qin2017_Tiamat125_HR/z0pt56.dat
astrodatapy/data/BHMF/Qin2017_Tiamat125_HR/z1pt00.dat
astrodatapy/data/BHMF/Qin2017_Tiamat125_HR/z2pt00.dat
astrodatapy/data/BHMF/Qin2017_Tiamat125_HR/z4pt02.dat
astrodatapy/data/BHMF/Qin2017_Tiamat125_HR/z5pt00.dat
astrodatapy/data/BHMF/Qin2017_Tiamat125_HR/z7pt96.dat
astrodatapy/data/BHMF/Shankar2009/z0pt0.dat
astrodatapy/data/BHMF/Shankar2009/z0pt5.dat
astrodatapy/data/BHMF/Shankar2009/z1pt0.dat
astrodatapy/data/BHMF/Shen2012/z0pt4.dat
astrodatapy/data/BHMF/Shen2012/z0pt6.dat
astrodatapy/data/BHMF/Shen2012/z0pt8.dat
astrodatapy/data/BHMF/Shen2012/z1pt0.dat
astrodatapy/data/BHMF/Shen2012/z1pt2.dat
astrodatapy/data/BHMF/Shen2012/z1pt4.dat
astrodatapy/data/BHMF/Shen2012/z1pt6.dat
astrodatapy/data/BHMF/Shen2012/z1pt8.dat
astrodatapy/data/BHMF/Shen2012/z2pt15.dat
astrodatapy/data/BHMF/Shen2012/z2pt65.dat
astrodatapy/data/BHMF/Shen2012/z3pt2.dat
astrodatapy/data/BHMF/Shen2012/z3pt75.dat
astrodatapy/data/BHMF/Shen2012/z4pt25.dat
astrodatapy/data/BHMF/Shen2012/z4pt75.dat
astrodatapy/data/BHMF/Vika2009/z0pt0.dat
astrodatapy/data/DiskSize_StellarMass/info.txt
astrodatapy/data/DiskSize_StellarMass/Bernardi2013/z0pt1.dat
astrodatapy-0.0.dev56.dist-info/DESCRIPTION.rst
astrodatapy-0.0.dev56.dist-info/METADATA
astrodatapy-0.0.dev56.dist-info/RECORD
astrodatapy-0.0.dev56.dist-info/WHEEL
astrodatapy-0.0.dev56.dist-info/entry_points.txt
astrodatapy-0.0.dev56.dist-info/metadata.json
astrodatapy-0.0.dev56.dist-info/top_level.txt
